pystructor/__init__.py
pystructor/decorator.py
pystructor/exceptions.py
pystructor/generator.py
pystructor/utils.py
pystructor-0.2.0.dist-info/licenses/LICENSE
pystructor-0.2.0.dist-info/METADATA
pystructor-0.2.0.dist-info/WHEEL
pystructor-0.2.0.dist-info/top_level.txt
pystructor-0.2.0.dist-info/RECORD
