Metadata-Version: 2.4
Name: Pystructor
Version: 0.2.0
Summary: A Python library inspired by TypeScript, featuring handy decorators for transforming Pydantic models and automatic CRUD schema generation.
Author-email: SadZip <sssad@zippp.ru>
Project-URL: Homepage, https://github.com/baryber/pystructor
Classifier: Programming Language :: Python :: 3
Classifier: Operating System :: OS Independent
Classifier: Framework :: Pydantic :: 2
Classifier: Topic :: Software Development :: Code Generators
Requires-Python: >=3.8
License-File: LICENSE
Requires-Dist: sqlmodel>=0.0.24
Requires-Dist: pydantic<3.0.0,>=2.0.0
Requires-Dist: sqlalchemy<3.0,>=2.0
Provides-Extra: test
Requires-Dist: pytest>=7.0.0; extra == "test"
Dynamic: license-file
